qwen3_asr_toolkit/__init__.py
qwen3_asr_toolkit/audio_tools.py
qwen3_asr_toolkit/call_api.py
qwen3_asr_toolkit/qwen3asr.py
qwen3_asr_toolkit-1.0.4.dist-info/licenses/LICENSE
qwen3_asr_toolkit-1.0.4.dist-info/METADATA
qwen3_asr_toolkit-1.0.4.dist-info/WHEEL
qwen3_asr_toolkit-1.0.4.dist-info/entry_points.txt
qwen3_asr_toolkit-1.0.4.dist-info/top_level.txt
qwen3_asr_toolkit-1.0.4.dist-info/RECORD
