Metadata-Version: 2.4
Name: qwen3-asr-toolkit
Version: 1.0.4
Summary: Python toolkit for the Qwen3-ASR API—parallel high‑throughput calls, robust long‑audio transcription, multi‑sample‑rate support.
Home-page: https://github.com/QwenLM/Qwen3-ASR-Toolkit
Author: He Wang
Author-email: hwang2001@mail.nwpu.edu.cn
Classifier: Programming Language :: Python :: 3
Classifier: Operating System :: OS Independent
Requires-Python: >=3.8
License-File: LICENSE
Requires-Dist: dashscope
Requires-Dist: librosa
Requires-Dist: soundfile
Requires-Dist: silero_vad
Requires-Dist: pydub
Requires-Dist: tqdm
Requires-Dist: numpy
Requires-Dist: srt
Dynamic: author
Dynamic: author-email
Dynamic: classifier
Dynamic: description
Dynamic: description-content-type
Dynamic: home-page
Dynamic: license-file
Dynamic: requires-dist
Dynamic: requires-python
Dynamic: summary
